{
  "updated": "2026-02-27T20:37:39Z",
  "data": {
    "sp": {
      "price": 6865.75,
      "chgPct": -0.63,
      "src": "GHA"
    },
    "ndq": {
      "price": 22620.11,
      "chgPct": -1.13,
      "src": "GHA"
    },
    "dji": {
      "price": 48913.71,
      "chgPct": -1.18,
      "src": "GHA"
    },
    "inr": {
      "price": 91.0,
      "chgPct": 0.05,
      "src": "GHA"
    },
    "crude": {
      "price": 67.19,
      "chgPct": 2.88,
      "src": "GHA"
    },
    "gold": {
      "price": 5278.6,
      "chgPct": 1.5,
      "src": "GHA"
    },
    "silver": {
      "price": 94.3,
      "chgPct": 4.62,
      "src": "GHA"
    },
    "n50": {
      "price": 25178.65,
      "chgPct": -1.23,
      "src": "GHA"
    },
    "bn": {
      "price": 60529.0,
      "chgPct": -0.93,
      "src": "GHA"
    },
    "sx": {
      "price": 81287.19,
      "chgPct": -1.17,
      "src": "GHA"
    },
    "fn": {
      "price": 27869.75,
      "chgPct": -1.45,
      "src": "GHA"
    },
    "vix": {
      "price": 13.7,
      "chgPct": 5.2,
      "src": "GHA"
    },
    "t_RELIANCE": {
      "price": 1393.9,
      "chgPct": -0.92,
      "src": "GHA"
    },
    "t_HDFCBANK": {
      "price": 887.75,
      "chgPct": -0.93,
      "src": "GHA"
    },
    "t_ICICIBANK": {
      "price": 1378.9,
      "chgPct": -1.85,
      "src": "GHA"
    },
    "t_INFY": {
      "price": 1300.1,
      "chgPct": 0.7,
      "src": "GHA"
    },
    "t_TCS": {
      "price": 2637.4,
      "chgPct": -0.42,
      "src": "GHA"
    },
    "t_AIRTEL": {
      "price": 1879.3,
      "chgPct": -2.61,
      "src": "GHA"
    },
    "t_ITC": {
      "price": 313.6,
      "chgPct": -1.52,
      "src": "GHA"
    },
    "t_SBI": {
      "price": 1201.7,
      "chgPct": -0.64,
      "src": "GHA"
    },
    "t_KOTAK": {
      "price": 415.2,
      "chgPct": -2.16,
      "src": "GHA"
    },
    "t_LT": {
      "price": 4278.3,
      "chgPct": -0.19,
      "src": "GHA"
    },
    "u_AAPL": {
      "price": 265.51,
      "chgPct": -2.21,
      "src": "GHA"
    },
    "u_MSFT": {
      "price": 393.38,
      "chgPct": -0.91,
      "src": "GHA"
    },
    "u_NVDA": {
      "price": 178.26,
      "chgPct": -3.73,
      "src": "GHA"
    },
    "u_AMZN": {
      "price": 208.88,
      "chgPct": 1.19,
      "src": "GHA"
    },
    "u_GOOGL": {
      "price": 307.42,
      "chgPct": -0.4,
      "src": "GHA"
    },
    "u_META": {
      "price": 640.21,
      "chgPct": -1.77,
      "src": "GHA"
    },
    "u_TSLA": {
      "price": 399.71,
      "chgPct": -1.74,
      "src": "GHA"
    },
    "u_BRK": {
      "price": 504.64,
      "chgPct": 0.73,
      "src": "GHA"
    },
    "u_JPM": {
      "price": 298.14,
      "chgPct": -1.92,
      "src": "GHA"
    },
    "u_UNH": {
      "price": 293.01,
      "chgPct": 2.34,
      "src": "GHA"
    }
  },
  "errors": []
}